easypost_python_toolkit/__init__.py
easypost_python_toolkit/__version__.py
easypost_python_toolkit/requirements.txt
easypost_python_toolkit/logging/__init__.py
easypost_python_toolkit/logging/elasticsearch/__init__.py
easypost_python_toolkit/logging/elasticsearch/elasticsearch_logger.py
easypost_python_toolkit/logging/elasticsearch/utilities.py
easypost_python_toolkit/mailing/__init__.py
easypost_python_toolkit/mailing/email_sender.py
easypost_python_toolkit/slack/__init__.py
easypost_python_toolkit/slack/slack_client.py
easypost_python_toolkit/sql_server/__init__.py
easypost_python_toolkit/sql_server/sql_server_database.py
easypost_python_toolkit-1.0.12.dist-info/METADATA
easypost_python_toolkit-1.0.12.dist-info/WHEEL
easypost_python_toolkit-1.0.12.dist-info/licenses/LICENSE
easypost_python_toolkit-1.0.12.dist-info/RECORD
